setup.py
celery_mongodb_nobinary_backend.egg-info/PKG-INFO
celery_mongodb_nobinary_backend.egg-info/SOURCES.txt
celery_mongodb_nobinary_backend.egg-info/dependency_links.txt
celery_mongodb_nobinary_backend.egg-info/requires.txt
celery_mongodb_nobinary_backend.egg-info/top_level.txt
zcelerybackend/__init__.py
zcelerybackend/mongodb.py