Metadata-Version: 1.0
Name: celery-mongodb-nobinary-backend
Version: 0.0.10
Summary: Celery backend for MongoDB that does not convert task results into a binary format before storing them in Mongo database.
Home-page: UNKNOWN
Author: Zakir Durumeric
Author-email: zakird@gmail.com
License: Apache License, Version 2.0
Keywords: python celery mongodb backend
Platform: UNKNOWN
